benas_filesync/__init__.py
benas_filesync/cli.py
benas_filesync/main.py
benas_filesync/manager.py
tests/__init__.py
tests/test_manager.py
benas_filesync-1.0.5.dist-info/METADATA
benas_filesync-1.0.5.dist-info/WHEEL
benas_filesync-1.0.5.dist-info/entry_points.txt
benas_filesync-1.0.5.dist-info/top_level.txt
benas_filesync-1.0.5.dist-info/RECORD
