Metadata-Version: 2.4
Name: benas_filesync
Version: 1.0.5
Summary: File synchronization script with backup and versioning
Home-page: https://github.com/BUntulis/filesync
Author: Benas Untulis
Author-email: untulisb@gmail.com
Classifier: Programming Language :: Python :: 3
Classifier: Operating System :: OS Independent
Requires-Python: >=3.6
Dynamic: author
Dynamic: author-email
Dynamic: classifier
Dynamic: description
Dynamic: description-content-type
Dynamic: home-page
Dynamic: requires-python
Dynamic: summary
